rez-stubs/__init__.pyi
rez-stubs/build_process.pyi
rez-stubs/build_system.pyi
rez-stubs/bundle_context.pyi
rez-stubs/command.pyi
rez-stubs/config.pyi
rez-stubs/deprecations.pyi
rez-stubs/developer_package.pyi
rez-stubs/exceptions.pyi
rez-stubs/package_bind.pyi
rez-stubs/package_cache.pyi
rez-stubs/package_copy.pyi
rez-stubs/package_filter.pyi
rez-stubs/package_help.pyi
rez-stubs/package_maker.pyi
rez-stubs/package_move.pyi
rez-stubs/package_order.pyi
rez-stubs/package_py_utils.pyi
rez-stubs/package_remove.pyi
rez-stubs/package_repository.pyi
rez-stubs/package_resources.pyi
rez-stubs/package_search.pyi
rez-stubs/package_serialise.pyi
rez-stubs/package_test.pyi
rez-stubs/packages.pyi
rez-stubs/pip.pyi
rez-stubs/plugin_managers.pyi
rez-stubs/py.typed
rez-stubs/release_hook.pyi
rez-stubs/release_vcs.pyi
rez-stubs/resolved_context.pyi
rez-stubs/resolver.pyi
rez-stubs/rex.pyi
rez-stubs/rex_bindings.pyi
rez-stubs/rezconfig.pyi
rez-stubs/serialise.pyi
rez-stubs/shells.pyi
rez-stubs/solver.pyi
rez-stubs/status.pyi
rez-stubs/suite.pyi
rez-stubs/system.pyi
rez-stubs/util.pyi
rez-stubs/wrapper.pyi
rez-stubs/bind/PyQt.pyi
rez-stubs/bind/PySide.pyi
rez-stubs/bind/__init__.pyi
rez-stubs/bind/_pymodule.pyi
rez-stubs/bind/_utils.pyi
rez-stubs/bind/arch.pyi
rez-stubs/bind/cmake.pyi
rez-stubs/bind/gcc.pyi
rez-stubs/bind/hello_world.pyi
rez-stubs/bind/os.pyi
rez-stubs/bind/pip.pyi
rez-stubs/bind/platform.pyi
rez-stubs/bind/python.pyi
rez-stubs/bind/rez.pyi
rez-stubs/bind/rezgui.pyi
rez-stubs/bind/setuptools.pyi
rez-stubs/bind/sip.pyi
rez-stubs/cli/__init__.pyi
rez-stubs/cli/_complete_util.pyi
rez-stubs/cli/_entry_points.pyi
rez-stubs/cli/_main.pyi
rez-stubs/cli/_util.pyi
rez-stubs/cli/benchmark.pyi
rez-stubs/cli/bind.pyi
rez-stubs/cli/build.pyi
rez-stubs/cli/bundle.pyi
rez-stubs/cli/complete.pyi
rez-stubs/cli/config.pyi
rez-stubs/cli/context.pyi
rez-stubs/cli/cp.pyi
rez-stubs/cli/depends.pyi
rez-stubs/cli/diff.pyi
rez-stubs/cli/env.pyi
rez-stubs/cli/forward.pyi
rez-stubs/cli/gui.pyi
types_rez-3.2.1.6.dist-info/METADATA
types_rez-3.2.1.6.dist-info/WHEEL
types_rez-3.2.1.6.dist-info/RECORD
