Metadata-Version: 2.4
Name: types-rez
Version: 3.2.1.6
Summary: python stubs for Rez
Author: Chad Dombrova
License-Expression: MIT
Keywords: 3d,CG,VFX,animation,games,graphics
Classifier: Development Status :: 4 - Beta
Classifier: Intended Audience :: Developers
Classifier: License :: OSI Approved :: MIT License
Classifier: Operating System :: OS Independent
Classifier: Programming Language :: Python :: 2
Classifier: Programming Language :: Python :: 3
